student_success_tool/__init__.py
student_success_tool/eda.py
student_success_tool/py.typed
student_success_tool/assets/pdp/features_table.toml
student_success_tool/configs/__init__.py
student_success_tool/configs/custom.py
student_success_tool/configs/pdp.py
student_success_tool/dataio/__init__.py
student_success_tool/dataio/assets.py
student_success_tool/dataio/models.py
student_success_tool/dataio/read.py
student_success_tool/dataio/write.py
student_success_tool/dataio/converters/__init__.py
student_success_tool/dataio/converters/pdp/__init__.py
student_success_tool/dataio/converters/pdp/raw_cohort.py
student_success_tool/dataio/converters/pdp/raw_course.py
student_success_tool/dataio/pdp/__init__.py
student_success_tool/dataio/pdp/raw_data.py
student_success_tool/dataio/schemas/__init__.py
student_success_tool/dataio/schemas/pdp/__init__.py
student_success_tool/dataio/schemas/pdp/labeled.py
student_success_tool/dataio/schemas/pdp/raw_cohort.py
student_success_tool/dataio/schemas/pdp/raw_course.py
student_success_tool/dataio/schemas/pdp/student_term.py
student_success_tool/generation/__init__.py
student_success_tool/generation/pdp/__init__.py
student_success_tool/generation/pdp/raw_cohort.py
student_success_tool/generation/pdp/raw_course.py
student_success_tool/ingestion_validation/README.md
student_success_tool/ingestion_validation/__init__.py
student_success_tool/ingestion_validation/base_schema.json
student_success_tool/ingestion_validation/generate_extensions.py
student_success_tool/ingestion_validation/logger.py
student_success_tool/ingestion_validation/validation.py
student_success_tool/modeling/__init__.py
student_success_tool/modeling/bias_detection.py
student_success_tool/modeling/evaluation.py
student_success_tool/modeling/feature_selection.py
student_success_tool/modeling/inference.py
student_success_tool/modeling/registration.py
student_success_tool/modeling/training.py
student_success_tool/modeling/utils.py
student_success_tool-0.3.10.dist-info/METADATA
student_success_tool-0.3.10.dist-info/WHEEL
student_success_tool-0.3.10.dist-info/licenses/LICENSE.md
student_success_tool-0.3.10.dist-info/RECORD
