Metadata-Version: 2.4
Name: student-success-tool
Version: 0.3.10
Summary: School-agnostic lib for implementing Student Success Tool workflows.
Project-URL: Repository, https://github.com/datakind/student-success-tool
License-File: LICENSE.md
Requires-Python: <3.13,>=3.10
Requires-Dist: databricks-connect~=16.0
Requires-Dist: databricks-sdk~=0.38.0
Requires-Dist: faker>=20.1
Requires-Dist: google-cloud-storage~=2.17
Requires-Dist: ipywidgets~=8.1
Requires-Dist: markdown~=3.5
Requires-Dist: matplotlib~=3.7
Requires-Dist: missingno~=0.5
Requires-Dist: mlflow~=2.13
Requires-Dist: numpy~=1.26
Requires-Dist: pandas~=2.0
Requires-Dist: pandera~=0.23.0
Requires-Dist: pyarrow~=16.0
Requires-Dist: pydantic~=2.10
Requires-Dist: pydyf~=0.8.0
Requires-Dist: pyyaml~=6.0
Requires-Dist: scikit-learn~=1.4
Requires-Dist: seaborn~=0.13
Requires-Dist: shap~=0.46.0
Requires-Dist: statsmodels~=0.14
Requires-Dist: tomli~=2.0; python_version < '3.11'
Requires-Dist: tomlkit==0.13.3
Requires-Dist: types-markdown~=3.8
Requires-Dist: weasyprint~=60.2
